MANIFEST.in
README.md
VERSION
setup.py
smpp/__init__.py
smpp/pdu/__init__.py
smpp/pdu/constants.py
smpp/pdu/encoding.py
smpp/pdu/enum.py
smpp/pdu/error.py
smpp/pdu/gsm_constants.py
smpp/pdu/gsm_encoding.py
smpp/pdu/gsm_types.py
smpp/pdu/namedtuple.py
smpp/pdu/operations.py
smpp/pdu/pdu_encoding.py
smpp/pdu/pdu_types.py
smpp/pdu/sm_encoding.py
smpp/pdu/smpp_time.py
smpp/pdu/tests/__init__.py
smpp/pdu/tests/test_gsm_encoding.py
smpp/pdu/tests/test_pdu_encoding.py
smpp/pdu/tests/test_pdu_types.py
smpp/pdu/tests/test_sm_encoding.py
smpp/pdu/tests/test_smpp_time.py
smpppdu.egg-info/PKG-INFO
smpppdu.egg-info/SOURCES.txt
smpppdu.egg-info/dependency_links.txt
smpppdu.egg-info/not-zip-safe
smpppdu.egg-info/top_level.txt