Metadata-Version: 2.1
Name: smpppdu
Version: 0.1.1
Summary: Library for parsing Protocol Data Units (PDUs) in SMPP protocol
Home-page: https://github.com/devtud/smpppdu
Author: Roger Hoover
Author-email: roger.hoover@gmail.com
License: Apache License 2.0
Project-URL: Source, https://github.com/devtud/smpppdu
Keywords: smpp pdu
Platform: UNKNOWN
Classifier: Development Status :: 5 - Production/Stable
Classifier: Topic :: System :: Networking
Classifier: Operating System :: OS Independent
Classifier: License :: OSI Approved :: Apache Software License
Classifier: Intended Audience :: Developers
Classifier: Programming Language :: Python :: 3.7
Classifier: Topic :: Software Development :: Libraries :: Python Modules
Requires-Python: >=3.7, <4
